{
  "project_info": {
    "project_number": "376487370634",
    "project_id": "businessapp-9b985",
    "storage_bucket": "businessapp-9b985.appspot.com"
  },
  "client": [
    {
      "client_info": {
        "mobilesdk_app_id": "1:376487370634:android:e07e1151d982cccf3f7273",
        "android_client_info": {
          "package_name": "com.aarlic.business_application"
        }
      },
      "oauth_client": [
        {
          "client_id": "376487370634-okogi784dt1qtj7rnvscn0v0j797li8a.apps.googleusercontent.com",
          "client_type": 3
        }
      ],
      "api_key": [
        {
          "current_key": "AIzaSyBPZDJcsPw-GFsj3CzWvYjO3tz02xEoYqM"
        }
      ],
      "services": {
        "appinvite_service": {
          "other_platform_oauth_client": [
            {
              "client_id": "376487370634-okogi784dt1qtj7rnvscn0v0j797li8a.apps.googleusercontent.com",
              "client_type": 3
            }
          ]
        }
      }
    }
  ],
  "configuration_version": "1"
}